check_orientation/__init__.py
check_orientation/dataloaders.py
check_orientation/inference.py
check_orientation/pre_trained_models.py
check_orientation/train.py
check_orientation-0.0.5.dist-info/LICENSE
check_orientation-0.0.5.dist-info/METADATA
check_orientation-0.0.5.dist-info/WHEEL
check_orientation-0.0.5.dist-info/top_level.txt
check_orientation-0.0.5.dist-info/RECORD
