Metadata-Version: 2.1
Name: check-orientation
Version: 0.0.5
Summary: Check if image was rotated by 90, 180, 270 degrees.
Home-page: https://github.com/ternaus/check_orientation
Author: Vladimir Iglovikov
License: MIT
Platform: UNKNOWN
Classifier: License :: OSI Approved :: MIT License
Classifier: Intended Audience :: Developers
Classifier: Intended Audience :: Science/Research
Classifier: Operating System :: OS Independent
Classifier: Programming Language :: Python
Classifier: Programming Language :: Python :: 3
Classifier: Topic :: Software Development :: Libraries
Classifier: Topic :: Software Development :: Libraries :: Python Modules
Requires-Dist: albumentations
Requires-Dist: iglovikov-helper-functions
Requires-Dist: timm
Requires-Dist: torch
Provides-Extra: test
Requires-Dist: pytest ; extra == 'test'
